{"customer_id": "C7", "basket": [{"product_id": "P54", "price": 1596}, {"product_id": "P58", "price": 184}, {"product_id": "P46", "price": 745}], "date_of_purchase": "2019-01-22 09:07:00"}
{"customer_id": "C12", "basket": [{"product_id": "P25", "price": 124}, {"product_id": "P30", "price": 375}], "date_of_purchase": "2019-01-22 12:41:00"}
{"customer_id": "C13", "basket": [{"product_id": "P31", "price": 1589}, {"product_id": "P23", "price": 1151}, {"product_id": "P23", "price": 1423}], "date_of_purchase": "2019-01-22 08:34:00"}
{"customer_id": "C21", "basket": [{"product_id": "P45", "price": 1451}], "date_of_purchase": "2019-01-22 14:11:00"}
{"customer_id": "C28", "basket": [{"product_id": "P22", "price": 1027}, {"product_id": "P32", "price": 1207}], "date_of_purchase": "2019-01-22 14:00:00"}
{"customer_id": "C31", "basket": [{"product_id": "P34", "price": 1255}, {"product_id": "P31", "price": 1769}, {"product_id": "P28", "price": 645}], "date_of_purchase": "2019-01-22 11:59:00"}
{"customer_id": "C33", "basket": [{"product_id": "P22", "price": 431}], "date_of_purchase": "2019-01-22 19:04:00"}
{"customer_id": "C36", "basket": [{"product_id": "P64", "price": 422}], "date_of_purchase": "2019-01-22 08:32:00"}
{"customer_id": "C37", "basket": [{"product_id": "P38", "price": 304}], "date_of_purchase": "2019-01-22 18:32:00"}
{"customer_id": "C42", "basket": [{"product_id": "P47", "price": 1480}], "date_of_purchase": "2019-01-22 17:51:00"}
{"customer_id": "C44", "basket": [{"product_id": "P05", "price": 1486}], "date_of_purchase": "2019-01-22 07:30:00"}
{"customer_id": "C45", "basket": [{"product_id": "P36", "price": 843}, {"product_id": "P40", "price": 1949}], "date_of_purchase": "2019-01-22 07:19:00"}
{"customer_id": "C51", "basket": [{"product_id": "P61", "price": 1031}, {"product_id": "P62", "price": 1330}, {"product_id": "P62", "price": 1929}], "date_of_purchase": "2019-01-22 07:00:00"}
{"customer_id": "C54", "basket": [{"product_id": "P34", "price": 1622}], "date_of_purchase": "2019-01-22 05:08:00"}
{"customer_id": "C63", "basket": [{"product_id": "P37", "price": 631}, {"product_id": "P38", "price": 632}, {"product_id": "P38", "price": 1467}], "date_of_purchase": "2019-01-22 08:15:00"}
{"customer_id": "C64", "basket": [{"product_id": "P11", "price": 493}], "date_of_purchase": "2019-01-22 18:58:00"}
{"customer_id": "C65", "basket": [{"product_id": "P32", "price": 824}], "date_of_purchase": "2019-01-22 04:36:00"}
{"customer_id": "C70", "basket": [{"product_id": "P40", "price": 164}, {"product_id": "P35", "price": 1167}, {"product_id": "P37", "price": 1668}], "date_of_purchase": "2019-01-22 18:52:00"}
{"customer_id": "C80", "basket": [{"product_id": "P03", "price": 1121}, {"product_id": "P02", "price": 107}, {"product_id": "P06", "price": 1610}], "date_of_purchase": "2019-01-22 06:52:00"}
{"customer_id": "C95", "basket": [{"product_id": "P37", "price": 859}, {"product_id": "P37", "price": 1401}], "date_of_purchase": "2019-01-22 20:50:00"}
{"customer_id": "C96", "basket": [{"product_id": "P22", "price": 206}, {"product_id": "P33", "price": 612}, {"product_id": "P27", "price": 179}], "date_of_purchase": "2019-01-22 03:01:00"}
{"customer_id": "C103", "basket": [{"product_id": "P52", "price": 1868}], "date_of_purchase": "2019-01-22 14:42:00"}
{"customer_id": "C105", "basket": [{"product_id": "P61", "price": 1373}, {"product_id": "P64", "price": 1023}, {"product_id": "P64", "price": 732}], "date_of_purchase": "2019-01-22 05:05:00"}
{"customer_id": "C106", "basket": [{"product_id": "P63", "price": 800}], "date_of_purchase": "2019-01-22 21:55:00"}
{"customer_id": "C110", "basket": [{"product_id": "P31", "price": 1120}, {"product_id": "P34", "price": 1392}, {"product_id": "P22", "price": 1022}], "date_of_purchase": "2019-01-22 06:46:00"}
{"customer_id": "C121", "basket": [{"product_id": "P40", "price": 1391}], "date_of_purchase": "2019-01-22 18:08:00"}
{"customer_id": "C131", "basket": [{"product_id": "P38", "price": 466}, {"product_id": "P37", "price": 147}, {"product_id": "P36", "price": 1898}], "date_of_purchase": "2019-01-22 03:40:00"}
{"customer_id": "C136", "basket": [{"product_id": "P30", "price": 989}], "date_of_purchase": "2019-01-22 13:17:00"}
